flask_staticdirs/__init__.py
flask_staticdirs-1.0.1.dist-info/LICENSE
flask_staticdirs-1.0.1.dist-info/METADATA
flask_staticdirs-1.0.1.dist-info/WHEEL
flask_staticdirs-1.0.1.dist-info/top_level.txt
flask_staticdirs-1.0.1.dist-info/RECORD
