Metadata-Version: 2.1
Name: flask-staticdirs
Version: 1.0.1
Summary: Creates a Flask blueprint to serve files and directories (with support for index files) from at static folder.
Home-page: https://github.com/pbatey/flask-staticdirs
Author: Phil Batey
Author-email: pbatey+pypi@gmail.com
License: MIT
Platform: UNKNOWN
Classifier: License :: OSI Approved :: MIT License
Classifier: Programming Language :: Python :: 3
Classifier: Programming Language :: Python :: 3.9
License-File: LICENSE
Requires-Dist: flask (>=2.1.0)
